.gitignore
README.md
setup.cfg
setup.py
eeutils/__init__.py
eeutils/_version.py
eeutils/config.py
eeutils/main.py
eeutils/parameters.py
eeutils/utils.py
eeutils.egg-info/PKG-INFO
eeutils.egg-info/SOURCES.txt
eeutils.egg-info/dependency_links.txt
eeutils.egg-info/entry_points.txt
eeutils.egg-info/not-zip-safe
eeutils.egg-info/requires.txt
eeutils.egg-info/top_level.txt
eeutils/bash/__init__.py
eeutils/bash/download_dump.py
eeutils/bash/restoredb.py
eeutils/bash/search.py
eeutils/git/__init__.py
eeutils/git/branchrm.py
eeutils/odoo/__init__.py
eeutils/odoo/fields.py
eeutils/odoo/groups.py
eeutils/odoo/sync_translations.py
eeutils/odoo/translate_module.py
eeutils/templates/auto_clean.sql