Metadata-Version: 2.1
Name: eeutils
Version: 1.0.0
Summary: Utility commands for Development
Home-page: https://gitlab.e-mips.com.ar/infra/eeutils
Author: Martín Nicolás Cuesta/Santiago Said
Author-email: cuesta.martin.n@hotmail.com
Maintainer: Eynes & E-MIPS
Maintainer-email: cuesta.martin.n@hotmail.com
License: AGPL3+
Platform: UNKNOWN
Classifier: Intended Audience :: Developers
Classifier: Intended Audience :: Information Technology
Classifier: Programming Language :: Python :: 2
Classifier: Programming Language :: Python :: 3
Classifier: Operating System :: OS Independent
